abodepy/__init__.py
abodepy/__main__.py
abodepy/automation.py
abodepy/event_controller.py
abodepy/exceptions.py
abodepy/socketio.py
abodepy/utils.py
abodepy/devices/__init__.py
abodepy/devices/alarm.py
abodepy/devices/binary_sensor.py
abodepy/devices/camera.py
abodepy/devices/cover.py
abodepy/devices/light.py
abodepy/devices/lock.py
abodepy/devices/sensor.py
abodepy/devices/switch.py
abodepy/devices/valve.py
abodepy/helpers/__init__.py
abodepy/helpers/constants.py
abodepy/helpers/errors.py
abodepy/helpers/timeline.py
abodepy-1.2.2.dist-info/LICENSE
abodepy-1.2.2.dist-info/METADATA
abodepy-1.2.2.dist-info/WHEEL
abodepy-1.2.2.dist-info/entry_points.txt
abodepy-1.2.2.dist-info/top_level.txt
abodepy-1.2.2.dist-info/RECORD
