Metadata-Version: 2.1
Name: abodepy
Version: 1.2.2
Summary: An Abode alarm Python library running on Python 3.
Home-page: https://github.com/MisterWil/abodepy
Author: Wil Schrader
Author-email: wilrader@gmail.com
License: MIT
Platform: any
Classifier: Intended Audience :: Developers
Classifier: License :: OSI Approved :: MIT License
Classifier: Operating System :: OS Independent
Classifier: Programming Language :: Python :: 3.6
Classifier: Topic :: Home Automation
Requires-Dist: requests (>=2.12.4)
Requires-Dist: lomond (>=0.3.3)
Requires-Dist: colorlog (>=3.0.1)
